pentest_report_generator/__init__.py
pentest_report_generator/__main__.py
pentest_report_generator/assets/FiraMono-Bold.ttf
pentest_report_generator/assets/FiraMono-Medium.ttf
pentest_report_generator/assets/FiraMono-Regular.ttf
pentest_report_generator/assets/FiraSans-Black.ttf
pentest_report_generator/assets/FiraSans-BlackItalic.ttf
pentest_report_generator/assets/FiraSans-Bold.ttf
pentest_report_generator/assets/FiraSans-BoldItalic.ttf
pentest_report_generator/assets/FiraSans-ExtraBold.ttf
pentest_report_generator/assets/FiraSans-ExtraBoldItalic.ttf
pentest_report_generator/assets/FiraSans-ExtraLight.ttf
pentest_report_generator/assets/FiraSans-ExtraLightItalic.ttf
pentest_report_generator/assets/FiraSans-Italic.ttf
pentest_report_generator/assets/FiraSans-Light.ttf
pentest_report_generator/assets/FiraSans-LightItalic.ttf
pentest_report_generator/assets/FiraSans-Medium.ttf
pentest_report_generator/assets/FiraSans-MediumItalic.ttf
pentest_report_generator/assets/FiraSans-Regular.ttf
pentest_report_generator/assets/FiraSans-SemiBold.ttf
pentest_report_generator/assets/FiraSans-SemiBoldItalic.ttf
pentest_report_generator/assets/FiraSans-Thin.ttf
pentest_report_generator/assets/FiraSans-ThinItalic.ttf
pentest_report_generator/assets/fonts.css
pentest_report_generator/assets/logo.svg
pentest_report_generator/assets/pygmentize.css
pentest_report_generator/assets/style.css
pentest_report_generator/cli.py
pentest_report_generator/core.py
pentest_report_generator/template.html.jinja2
pentest_report_generator-0.1.6.dist-info/entry_points.txt
pentest_report_generator-0.1.6.dist-info/LICENSE
pentest_report_generator-0.1.6.dist-info/WHEEL
pentest_report_generator-0.1.6.dist-info/METADATA
pentest_report_generator-0.1.6.dist-info/RECORD
