Metadata-Version: 2.1
Name: pentest-report-generator
Version: 0.1.6
Summary: Generate penetration testing report from markdown files
Home-page: https://gitlab.com/staticnoise/pentest-report-generator
License: MIT
Keywords: HTML,Markdown,PDF,Penetration test
Author: Adam Chovanec
Author-email: business@adamchovanec.cz
Requires-Python: >=3.10,<4.0
Classifier: Development Status :: 3 - Alpha
Classifier: License :: OSI Approved :: MIT License
Classifier: Operating System :: OS Independent
Classifier: Programming Language :: Python :: 3
Classifier: Programming Language :: Python :: 3.10
Classifier: Programming Language :: Python :: 3.11
Classifier: Topic :: Documentation
Classifier: Topic :: Text Processing :: Markup :: HTML
Classifier: Topic :: Text Processing :: Markup :: Markdown
Classifier: Topic :: Utilities
Requires-Dist: Jinja2 (>=3.1.2,<4.0.0)
Requires-Dist: Markdown (>=3.4.1,<4.0.0)
Requires-Dist: Pygments (>=2.13.0,<3.0.0)
Requires-Dist: bleach (>=5.0.1,<6.0.0)
Requires-Dist: click (>=8.1.3,<9.0.0)
Requires-Dist: pymdown-extensions (>=9.7,<10.0)
Requires-Dist: python-slugify (>=6.1.2,<7.0.0)
Requires-Dist: weasyprint (>=57.0,<58.0)
Project-URL: Repository, https://gitlab.com/staticnoise/pentest-report-generator
